{
  "project_info": {
    "project_number": "1060136144187",
    "project_id": "flutter-test-f5ce5",
    "storage_bucket": "flutter-test-f5ce5.appspot.com"
  },
  "client": [
    {
      "client_info": {
        "mobilesdk_app_id": "1:1060136144187:android:afa8695c119bf91ac17b1e",
        "android_client_info": {
          "package_name": "com.example.ecommerce_application_01"
        }
      },
      "oauth_client": [],
      "api_key": [
        {
          "current_key": "AIzaSyBn42V3-NosPPAuS087q2zKbIYwRC76oRc"
        }
      ],
      "services": {
        "appinvite_service": {
          "other_platform_oauth_client": []
        }
      }
    }
  ],
  "configuration_version": "1"
}